README.md
setup.cfg
setup.py
primer_2020/__init__.py
primer_2020/cli.py
primer_2020_krzysiek.egg-info/PKG-INFO
primer_2020_krzysiek.egg-info/SOURCES.txt
primer_2020_krzysiek.egg-info/dependency_links.txt
primer_2020_krzysiek.egg-info/entry_points.txt
primer_2020_krzysiek.egg-info/requires.txt
primer_2020_krzysiek.egg-info/top_level.txt