Metadata-Version: 2.1
Name: primer-2020-krzysiek
Version: 0.2.1
Summary: Utility functions for prime numbers
Home-page: UNKNOWN
Author: Krzysztof Swidergal
Author-email: krzysiek.swider@gmail.com
License: MIT
Platform: UNKNOWN
